script/__init__.py
script/org/__init__.py
script/org/validator/__init__.py
script/org/validator/base_validator.py
script/org/validator/common_util.py
script/org/validator/config.py
script/org/validator/data_validator.py
script/org/validator/date_format_validator.py
script/org/validator/equal_validator.py
script/org/validator/not_equal_validator.py
script/org/validator/not_null_validator.py
script/org/validator/type_validator.py
script/org/validator/constant/__init__.py
script/org/validator/constant/constant.py
pyspark_data_validation_utils-0.0.21.dist-info/METADATA
pyspark_data_validation_utils-0.0.21.dist-info/WHEEL
pyspark_data_validation_utils-0.0.21.dist-info/top_level.txt
pyspark_data_validation_utils-0.0.21.dist-info/RECORD
