Metadata-Version: 2.1
Name: pyspark-data-validation-utils
Version: 0.0.21
Summary: Its Data cleansing tool, meant for Pyspark projects. 
Home-page: https://github.com/vikassingh1000/pyspark_data_validation_utils
Author: Vikas Singh
Author-email: vikassingh1000@gmail.com
License: APACHE
Keywords: Pyspark
Platform: UNKNOWN
Classifier: Development Status :: 3 - Alpha
Classifier: Topic :: Utilities
Classifier: License :: OSI Approved :: BSD License
